{"type":"FeatureCollection","crs":{"type":"name","properties":{"name":"EPSG:4326"}},"features":[{"type":"Feature","id":0,"geometry":{"type":"Point","coordinates":[-73.129619806999983,-15.928838391999932]},"properties":{"FID":0,"N°":406,"CUI":"2430024","FECHA":1759190400000,"JERARQUIA":"RVV","COD_RUTA":"R","RUTA_RECLA":"-","IDDPTO":"04","IDPROV":"0406","DPTO":"AREQUIPA","PROV":"CONDESUYOS","NOM_PUENTE":"ALTO MOLINO","HITO_KM":"-","LONGITUD_m":150,"CLASE":"DEFINITIVO","CONDICION":"MALO","N_CARRILES":2,"A_CALZADA":8.4000000000000004,"N_CONVENIO":"-","INVENTARIO":"-","ZONA_UTM":"18S","FUENTE":"GIE","CARTERA":"RCC","COMENTARIO":"LEY Nº 30556 RECONSTRUCCIÓN CON CAMBIOS, EXIME A FIRMA DE CONVENIOS CON LOS GOBIERNO LOCALES Y REGIONALES","A_F_A_PCTJ":"29.54 %","CUI_":2430024,"CUI_12":2430024,"NOMBRE_COR":"REHABILITACION DE PUENTE ALTO MOLINO Y ACCESOS","COSTO":47710844.810000002,"NOMBRE_LAR":"REHABILITACION DE PUENTE ALTO MOLINO Y ACCESOS","PMI":"NO PMI","PMI_AACTUA":0}}]}